<?xml version="1.0" encoding="UTF-8"?>
<QCARConfig xmlns:xsi="http://www.w3.org/2001/XMLSchema-instance" xsi:noNamespaceSchemaLocation="qcar_config.xsd">
  <Tracking>
    <ImageTarget name="21_the_world" size="0.088000 0.148500" />
    <ImageTarget name="20_judgement" size="0.088000 0.148500" />
    <ImageTarget name="19_the_sun" size="0.088000 0.148500" />
    <ImageTarget name="18_the_moon" size="0.088000 0.148500" />
    <ImageTarget name="17_the_star" size="0.088000 0.148500" />
    <ImageTarget name="16_the_tower" size="0.088000 0.148500" />
    <ImageTarget name="15_the_devil" size="0.088000 0.148500" />
    <ImageTarget name="14_temperance" size="0.088000 0.148500" />
    <ImageTarget name="13_death" size="0.088000 0.148500" />
    <ImageTarget name="12_the_hanged_man" size="0.088000 0.148500" />
    <ImageTarget name="11_justice" size="0.088000 0.148500" />
    <ImageTarget name="10_wheel_of_fortune" size="0.088000 0.148500" />
    <ImageTarget name="9_the_hermit" size="0.088000 0.148500" />
    <ImageTarget name="8_stregth" size="0.880000 1.485000" />
    <ImageTarget name="7_the_chariot" size="0.088000 0.148500" />
    <ImageTarget name="6_the_lovers" size="0.088000 0.148500" />
    <ImageTarget name="5_the_hierophant" size="0.088000 0.148500" />
    <ImageTarget name="4_the_emperor" size="0.088000 0.148500" />
    <ImageTarget name="3_the_empress" size="0.088000 0.148500" />
    <ImageTarget name="2_the_high_priestess" size="0.088000 0.148500" />
    <ImageTarget name="1_the_magician" size="0.088000 0.148500" />
    <ImageTarget name="0_the_fool" size="0.088000 0.148500" />
  </Tracking>
</QCARConfig>
